fancyDES/__init__.py
fancyDES/fancyDES.py
fancyDES/sbox.py
fancyDES-0.1.0.dist-info/LICENSE
fancyDES-0.1.0.dist-info/METADATA
fancyDES-0.1.0.dist-info/WHEEL
fancyDES-0.1.0.dist-info/top_level.txt
fancyDES-0.1.0.dist-info/RECORD
