Metadata-Version: 2.1
Name: fancyDES
Version: 0.1.0
Summary: DES Custom with Fancy Algorithm
Home-page: https://github.com/berv-uni-project/fancy-DES-algorithm
Author: Bervianto Leo Pratama
Author-email: bervianto.leo@gmail.com
License: UNKNOWN
Platform: UNKNOWN
Classifier: Programming Language :: Python :: 3
Classifier: License :: OSI Approved :: MIT License
Classifier: Operating System :: OS Independent
Requires-Python: >=3.6
Requires-Dist: numpy
